timelooper/__init__.py
timelooper/looptime.py
timelooper-0.1.2.dist-info/LICENSE
timelooper-0.1.2.dist-info/WHEEL
timelooper-0.1.2.dist-info/METADATA
timelooper-0.1.2.dist-info/RECORD
