Metadata-Version: 2.1
Name: timelooper
Version: 0.1.2
Summary: Timed loops made simple
Home-page: https://github.com/monomonedula/timelooper
License: MIT
Keywords: asyncio,utility
Author: monomonedula
Author-email: valh@tuta.io
Requires-Python: >=3.8,<4.0
Classifier: License :: OSI Approved :: MIT License
Classifier: Programming Language :: Python :: 3
Classifier: Programming Language :: Python :: 3.10
Classifier: Programming Language :: Python :: 3.8
Classifier: Programming Language :: Python :: 3.9
Project-URL: Repository, https://github.com/monomonedula/timelooper
